ezio/__init__.py
ezio/blueprint.py
ezio/base/__init__.py
ezio/base/bar.py
ezio/base/chart.py
ezio/base/distribution.py
ezio/base/line.py
ezio/base/rule.py
ezio/base/scatter.py
ezioaltair-0.1.2.dist-info/licenses/LICENSE
ezioaltair-0.1.2.dist-info/METADATA
ezioaltair-0.1.2.dist-info/WHEEL
ezioaltair-0.1.2.dist-info/top_level.txt
ezioaltair-0.1.2.dist-info/RECORD
