Metadata-Version: 2.4
Name: ezioaltair
Version: 0.1.2
Summary: A simple, opinionated wrapper for Altair visualizations.
Home-page: https://github.com/clarkmaio/ezio
Author: clarkmaio
Author-email: maioliandrea0@gmail.com
Keywords: altair data-visualization plotting wrapper
Classifier: Programming Language :: Python :: 3
Classifier: License :: OSI Approved :: MIT License
Classifier: Operating System :: OS Independent
Classifier: Topic :: Scientific/Engineering :: Visualization
Requires-Python: >=3.10
License-File: LICENSE
Requires-Dist: altair>=5.0
Requires-Dist: polars
Dynamic: author
Dynamic: author-email
Dynamic: classifier
Dynamic: description
Dynamic: description-content-type
Dynamic: home-page
Dynamic: keywords
Dynamic: license-file
Dynamic: requires-dist
Dynamic: requires-python
Dynamic: summary
